promql_http_api/__init__.py
promql_http_api/alerts.py
promql_http_api/alertsmanagers.py
promql_http_api/api.py
promql_http_api/api_endpoint.py
promql_http_api/api_response.py
promql_http_api/buildinfo.py
promql_http_api/config.py
promql_http_api/flags.py
promql_http_api/format_query.py
promql_http_api/http_config.py
promql_http_api/label_values.py
promql_http_api/labels.py
promql_http_api/py.typed
promql_http_api/query.py
promql_http_api/rules.py
promql_http_api/runtimeinfo.py
promql_http_api/series.py
promql_http_api/targets.py
promql_http_api-0.3.4.dist-info/LICENSE.md
promql_http_api-0.3.4.dist-info/METADATA
promql_http_api-0.3.4.dist-info/NOTICE.md
promql_http_api-0.3.4.dist-info/WHEEL
promql_http_api-0.3.4.dist-info/RECORD
