Metadata-Version: 2.1
Name: promql-http-api
Version: 0.3.4
Summary: Query a Prometheus server and get a Pandas DataFrame
Home-page: https://github.com/nir-arad/promql-http-api
License: Apache-2.0
Keywords: prometheus,promql,pandas,dataframe
Author: Nir Arad
Requires-Python: >=3.9
Classifier: Development Status :: 3 - Alpha
Classifier: Intended Audience :: Developers
Classifier: License :: OSI Approved :: Apache Software License
Classifier: Operating System :: OS Independent
Classifier: Programming Language :: Python :: 3
Classifier: Programming Language :: Python :: 3.9
Classifier: Programming Language :: Python :: 3.10
Classifier: Programming Language :: Python :: 3.11
Classifier: Programming Language :: Python :: 3.12
Classifier: Programming Language :: Python :: 3 :: Only
Classifier: Programming Language :: Python :: 3.8
Requires-Dist: httpx (>=0.27.0)
Requires-Dist: numpy (>=2.0.0)
Requires-Dist: pandas (>=2.0.0)
Requires-Dist: requests (>=2.31.0)
Requires-Dist: types-setuptools (>=68.0.0)
Project-URL: Bug Tracker, https://github.com/nir-arad/promql-http-api/issues
Project-URL: Repository, https://github.com/nir-arad/promql-http-api
